skforecast/__init__.py
skforecast/base/__init__.py
skforecast/base/_forecaster_base.py
skforecast/datasets/__init__.py
skforecast/datasets/datasets.py
skforecast/deep_learning/__init__.py
skforecast/deep_learning/_forecaster_rnn.py
skforecast/deep_learning/utils.py
skforecast/direct/__init__.py
skforecast/direct/_forecaster_direct.py
skforecast/direct/_forecaster_direct_multivariate.py
skforecast/drift_detection/__init__.py
skforecast/drift_detection/_population_drift.py
skforecast/drift_detection/_range_drift.py
skforecast/exceptions/__init__.py
skforecast/exceptions/exceptions.py
skforecast/experimental/__init__.py
skforecast/experimental/_experimental.py
skforecast/feature_selection/__init__.py
skforecast/feature_selection/feature_selection.py
skforecast/metrics/__init__.py
skforecast/metrics/metrics.py
skforecast/model_selection/__init__.py
skforecast/model_selection/_search.py
skforecast/model_selection/_split.py
skforecast/model_selection/_utils.py
skforecast/model_selection/_validation.py
skforecast/plot/__init__.py
skforecast/plot/plot.py
skforecast/preprocessing/__init__.py
skforecast/preprocessing/preprocessing.py
skforecast/recursive/__init__.py
skforecast/recursive/_forecaster_equivalent_date.py
skforecast/recursive/_forecaster_recursive.py
skforecast/recursive/_forecaster_recursive_classifier.py
skforecast/recursive/_forecaster_recursive_multiseries.py
skforecast/recursive/_forecaster_stats.py
skforecast/stats/__init__.py
skforecast/stats/_arar.py
skforecast/stats/_arima.py
skforecast/stats/_ets.py
skforecast/stats/_sarimax.py
skforecast/stats/_utils.py
skforecast/stats/arar/__init__.py
skforecast/stats/arar/_arar_base.py
skforecast/stats/arima/__init__.py
skforecast/stats/arima/_arima_base.py
skforecast/stats/arima/_auto_arima.py
skforecast/stats/exponential_smoothing/__init__.py
skforecast/stats/exponential_smoothing/_ets_base.py
skforecast/stats/seasonal/__init__.py
skforecast/stats/seasonal/_differencing.py
skforecast-0.20.0.dist-info/licenses/CITATION.cff
skforecast-0.20.0.dist-info/licenses/LICENSE
skforecast-0.20.0.dist-info/METADATA
skforecast-0.20.0.dist-info/WHEEL
skforecast-0.20.0.dist-info/top_level.txt
skforecast-0.20.0.dist-info/RECORD
