Metadata-Version: 2.4
Name: skforecast
Version: 0.20.0
Summary: Skforecast is a Python library for time series forecasting using statistical and machine learning models. It works with any estimator compatible with the scikit-learn API, including popular options like LightGBM, XGBoost, CatBoost, Keras, and many others.
Author-email: Joaquin Amat Rodrigo <j.amatrodrigo@gmail.com>, Javier Escobar Ortiz <javier.escobar.ortiz@gmail.com>
Maintainer-email: Joaquin Amat Rodrigo <j.amatrodrigo@gmail.com>, Javier Escobar Ortiz <javier.escobar.ortiz@gmail.com>
License-Expression: BSD-3-Clause
Project-URL: Homepage, https://www.skforecast.org
Project-URL: Repository, https://github.com/skforecast/skforecast
Project-URL: Documentation, https://www.skforecast.org
Project-URL: Release Notes, https://skforecast.org/latest/releases/releases
Project-URL: Download, https://pypi.org/project/skforecast/#files
Project-URL: Tracker, https://github.com/skforecast/skforecast/issues
Keywords: data-science,machine-learning,data-mining,time-series,scikit-learn,forecasting,time-series-analysis,time-series-regression,autoregressive,deep-learning,lightgbm,xgboost
Classifier: Development Status :: 5 - Production/Stable
Classifier: Intended Audience :: Developers
Classifier: Intended Audience :: Science/Research
Classifier: Operating System :: MacOS
Classifier: Operating System :: Microsoft :: Windows
Classifier: Operating System :: POSIX
Classifier: Operating System :: Unix
Classifier: Programming Language :: Python
Classifier: Programming Language :: Python :: 3
Classifier: Programming Language :: Python :: 3.10
Classifier: Programming Language :: Python :: 3.11
Classifier: Programming Language :: Python :: 3.12
Classifier: Programming Language :: Python :: 3.13
Classifier: Programming Language :: Python :: 3.14
Classifier: Topic :: Software Development
Classifier: Topic :: Scientific/Engineering
Classifier: Topic :: Scientific/Engineering :: Artificial Intelligence
Requires-Python: >=3.10
License-File: LICENSE
License-File: CITATION.cff
Requires-Dist: numpy>=1.24
Requires-Dist: pandas<3.0,>=1.5
Requires-Dist: tqdm>=4.57
Requires-Dist: scikit-learn>=1.2
Requires-Dist: scipy>=1.3.2
Requires-Dist: optuna>=2.10
Requires-Dist: joblib>=1.1
Requires-Dist: numba>=0.59
Requires-Dist: rich>=13.9
Provides-Extra: stats
Requires-Dist: statsmodels<0.15,>=0.12; extra == "stats"
Provides-Extra: plotting
Requires-Dist: matplotlib<3.11,>=3.3; extra == "plotting"
Requires-Dist: seaborn<0.14,>=0.11; extra == "plotting"
Requires-Dist: statsmodels<0.15,>=0.12; extra == "plotting"
Provides-Extra: deeplearning
Requires-Dist: keras<4.0,>=3.0; extra == "deeplearning"
Requires-Dist: matplotlib<3.11,>=3.3; extra == "deeplearning"
Provides-Extra: all
Requires-Dist: matplotlib<3.11,>=3.3; extra == "all"
Requires-Dist: seaborn<0.14,>=0.11; extra == "all"
Requires-Dist: statsmodels<0.15,>=0.12; extra == "all"
Requires-Dist: keras<4.0,>=3.0; extra == "all"
Requires-Dist: tensorflow<2.21,>=2.18; python_version < "3.14" and extra == "all"
Requires-Dist: torch<2.11,>=2.4; extra == "all"
Provides-Extra: full
Requires-Dist: skforecast[all]; extra == "full"
Provides-Extra: docs
Requires-Dist: mike==2.1.3; extra == "docs"
Requires-Dist: mkdocs==1.6.1; extra == "docs"
Requires-Dist: mkdocs-jupyter==0.25.1; extra == "docs"
Requires-Dist: mkdocs-material==9.7.0; extra == "docs"
Requires-Dist: mkdocstrings==0.30.1; extra == "docs"
Requires-Dist: mkdocstrings-python==1.19.0; extra == "docs"
Requires-Dist: notebook==6.5.7; extra == "docs"
Requires-Dist: jupyter-contrib-nbextensions==0.7.0; extra == "docs"
Requires-Dist: black==25.11.0; extra == "docs"
Provides-Extra: test
Requires-Dist: pytest>=7.3; extra == "test"
Requires-Dist: pytest-cov>=4.1; extra == "test"
Requires-Dist: pytest-xdist>=3.3; extra == "test"
Requires-Dist: statsmodels<0.15,>=0.12; extra == "test"
Requires-Dist: matplotlib<3.11,>=3.3; extra == "test"
Requires-Dist: seaborn<0.14,>=0.11; extra == "test"
Requires-Dist: lightgbm<5.0,>=4.0; extra == "test"
Requires-Dist: xgboost<4.0,>=2.1; extra == "test"
Requires-Dist: keras<4.0,>=3.0; extra == "test"
Requires-Dist: torch<2.11,>=2.4; extra == "test"
Requires-Dist: tomli>=2.0; extra == "test"
Requires-Dist: pandas[parquet]>=1.5; extra == "test"
Dynamic: license-file
